setup.py
mkdocs_pandoc/__init__.py
mkdocs_pandoc/exceptions.py
mkdocs_pandoc/pandoc_converter.py
mkdocs_pandoc.egg-info/PKG-INFO
mkdocs_pandoc.egg-info/SOURCES.txt
mkdocs_pandoc.egg-info/dependency_links.txt
mkdocs_pandoc.egg-info/entry_points.txt
mkdocs_pandoc.egg-info/requires.txt
mkdocs_pandoc.egg-info/top_level.txt
mkdocs_pandoc/cli/__init__.py
mkdocs_pandoc/cli/mkdocs2pandoc.py
mkdocs_pandoc/filters/__init__.py
mkdocs_pandoc/filters/anchors.py
mkdocs_pandoc/filters/chapterhead.py
mkdocs_pandoc/filters/exclude.py
mkdocs_pandoc/filters/headlevels.py
mkdocs_pandoc/filters/images.py
mkdocs_pandoc/filters/include.py
mkdocs_pandoc/filters/tables.py
mkdocs_pandoc/filters/toc.py
mkdocs_pandoc/filters/xref.py