Metadata-Version: 1.1
Name: mkdocs-pandoc
Version: 0.2.3
Summary: A translator from mkdocs style markdown to pandoc style markdown
Home-page: https://github.com/jgrassler/mkdocs-pandoc
Author: Johannes Grassler
Author-email: johannes@btw23.de
License: Apache
Keywords: mkdoc markdown pandoc
Platform: UNKNOWN
Classifier: Development Status :: 3 - Alpha
Classifier: Intended Audience :: End Users/Desktop
Classifier: Intended Audience :: Developers
Classifier: Intended Audience :: Information Technology
Classifier: Intended Audience :: System Administrators
Classifier: Topic :: Documentation
Classifier: Topic :: Text Processing
Classifier: License :: OSI Approved :: Apache Software License
Classifier: Programming Language :: Python :: 2.7
